setup.py
samsara_sdk/__init__.py
samsara_sdk/client.py
samsara_sdk/constants.py
samsara_sdk/helpers.py
samsara_sdk.egg-info/PKG-INFO
samsara_sdk.egg-info/SOURCES.txt
samsara_sdk.egg-info/dependency_links.txt
samsara_sdk.egg-info/top_level.txt