Metadata-Version: 1.0
Name: samsara-sdk
Version: 0.5.5.0
Summary: A Python Client for Samsaza's Ingestion-API
Home-page: https://github.com/samsara/samsara
Author: Samsara Developers
Author-email: samsara.systems+info@gmail.com
License: UNKNOWN
Keywords: analytics,client,samsara
Platform: any
